data_transfer-1.0.9.data/scripts/data-transfer
data_transfer-1.0.9.dist-info/DESCRIPTION.rst
data_transfer-1.0.9.dist-info/METADATA
data_transfer-1.0.9.dist-info/RECORD
data_transfer-1.0.9.dist-info/WHEEL
data_transfer-1.0.9.dist-info/metadata.json
data_transfer-1.0.9.dist-info/top_level.txt
datatransfer/__init__.py
datatransfer/settings.py
datatransfer/storage.py
datatransfer/tasks.py
datatransfer/utils.py
