Metadata-Version: 2.0
Name: data-transfer
Version: 1.0.9
Summary: A data movement app that can use different source/targets tomove data around.
Home-page: https://github.com/UKHomeOffice/data-transfer
Author: Aker Systems
Author-email: development@akersystems.com
License: BSD
Keywords: data movement ftp sftp s3 buckets ingest
Platform: UNKNOWN
Classifier: Development Status :: 3 - Alpha
Classifier: Topic :: Utilities
Classifier: License :: OSI Approved :: BSD License
